visualization_toolkit/__init__.py
visualization_toolkit/_version.py
visualization_toolkit/adapters/__init__.py
visualization_toolkit/adapters/mse_experiment.py
visualization_toolkit/core/__init__.py
visualization_toolkit/core/aggregation.py
visualization_toolkit/metrics/__init__.py
visualization_toolkit/metrics/mse.py
visualization_toolkit/plots/__init__.py
visualization_toolkit/plots/_boxplot_utils.py
visualization_toolkit/plots/_significance_boxplot.py
visualization_toolkit/plots/boxplot.py
visualization_toolkit/plots/mse.py
visualization_toolkit/styles/__init__.py
visualization_toolkit/styles/boxplot.py
visualization_toolkit/styles/line.py
visualization_toolkit-0.1.0.dev61.dist-info/licenses/LICENSE
visualization_toolkit-0.1.0.dev61.dist-info/METADATA
visualization_toolkit-0.1.0.dev61.dist-info/WHEEL
visualization_toolkit-0.1.0.dev61.dist-info/top_level.txt
visualization_toolkit-0.1.0.dev61.dist-info/RECORD
