Metadata-Version: 2.4
Name: visualization-toolkit
Version: 0.1.0.dev61
Author-email: Aleksandr Sinitca <siniza.s.94@gmail.com>, Asya Lyanova <lyanova.ai@gmail.com>
License-Expression: Apache-2.0
Project-URL: Repository, https://github.com/Digiratory/visualization-toolkit.git
Requires-Python: >=3.10
License-File: LICENSE
Requires-Dist: numpy>=2.0
Requires-Dist: pandas>=2.2
Requires-Dist: matplotlib>=3.10
Provides-Extra: stats
Requires-Dist: scipy>=1.9; extra == "stats"
Dynamic: license-file
